{
  "entries": [
    {
      "title": "Entry 1",
      "date": "2023-08-01",
      "content": "This is the content of entry 1.",
      "id": 1
    },
    {
      "title": "Entry 2",
      "date": "2023-08-02",
      "content": "This is the content of entry 2.",
      "id": 2
    },
    {
      "title": "This is my third entry!",
      "date": "08/08/2023",
      "content": "This is the information I provided in my third entry. ",
      "id": 3
    },
    {
      "title": "I was born!",
      "date": "14/05/2004",
      "content": "Hi, I am born!",
      "id": 4
    },
    {
      "title": "Hello world!",
      "date": "07/08/2023",
      "content": "Today, I went to the gym :)",
      "id": 5
    }
  ]
}